MANIFEST.in
Makefile
README.md
README.rst
__version__.py
requirements.txt
setup.py
taoge_blog/__init__.py
taoge_blog/about_tech.rst
taoge_blog/conf.py
taoge_blog/favicon.ico
taoge_blog/feed.rst
taoge_blog/hadoop_intro.rst
taoge_blog/index.rst
taoge_blog/intercom_intro.rst
taoge_blog/me.rst
taoge_blog/other_platform.rst
taoge_blog.egg-info/PKG-INFO
taoge_blog.egg-info/SOURCES.txt
taoge_blog.egg-info/dependency_links.txt
taoge_blog.egg-info/not-zip-safe
taoge_blog.egg-info/requires.txt
taoge_blog.egg-info/top_level.txt
taoge_blog/_static/eclipse_config_jar_source.png
taoge_blog/_static/hadoop_client_service_provider.png
taoge_blog/_static/knowledge_base.png
taoge_blog/_static/logo.png
taoge_blog/_static/plan.png
taoge_blog/_static/yarn_archi.png
taoge_blog/_templates/layout.html
taoge_blog/hadoop/hadoop_install.rst
taoge_blog/hadoop/map_reduce.rst
taoge_blog/hadoop/yarn_debug.rst
taoge_blog/manage/time_manage.rst
taoge_blog/ml/machine_learning_notes.rst
taoge_blog/my_projects/search_job.rst
taoge_blog/thoughts/100_times_effective_programmer.rst
taoge_blog/thoughts/find_job_by_github.rst
taoge_blog/thoughts/is_k8s_the_google_gift.rst
taoge_blog/thoughts/knowledge_base.rst
taoge_blog/thoughts/why_we_communicate.rst
taoge_blog/travel/koland.rst
taoge_blog/travel/thailand_2017_06_15.rst
taoge_blog/travel/thoughts_in_another_country.rst