Metadata-Version: 1.1
Name: taoge-blog
Version: 0.0.3
Summary: [Taoge Blog](https://yowenter.github.io)
Home-page: https://github.com/yowenter/yowenter.github.io
Author: Wenter W
Author-email: wenter.wu@gmail.com
License: MIT License
Keywords: taoge blog; yowenter; taoge's thoughts; wenter.wu#gmail
Platform: UNKNOWN
Classifier: Programming Language :: Python :: 2.7
